[{"id":"Standard","realm":"pc","url":"https://www.pathofexile.com/ladders/league/Standard","startAt":"2013-01-23T21:00:00Z","endAt":null,"description":"The default game mode.","registerAt":"2019-09-06T19:00:00Z","delveEvent":true,"rules":[]},{"id":"Hardcore","realm":"pc","url":"https://www.pathofexile.com/ladders/league/Hardcore","startAt":"2013-01-23T21:00:00Z","endAt":null,"description":"A character killed in the Hardcore league is moved to the Standard league.","registerAt":"2019-09-06T19:00:00Z","delveEvent":true,"rules":[{"id":"Hardcore","name":"Hardcore","description":"A character killed in Hardcore is moved to its parent league."}]},{"id":"SSF Standard","realm":"pc","url":"https://www.pathofexile.com/ladders/league/SSF+Standard","startAt":"2013-01-23T21:00:00Z","endAt":null,"description":"SSF Standard","registerAt":"2019-09-06T19:00:00Z","delveEvent":true,"rules":[{"id":"NoParties","name":"Solo","description":"You may not party in this league."}]},{"id":"SSF Hardcore","realm":"pc","url":"https://www.pathofexile.com/ladders/league/SSF+Hardcore","startAt":"2013-01-23T21:00:00Z","endAt":null,"description":"SSF Hardcore","registerAt":"2019-09-06T19:00:00Z","delveEvent":true,"rules":[{"id":"Hardcore","name":"Hardcore","description":"A character killed in Hardcore is moved to its parent league."},{"id":"NoParties","name":"Solo","description":"You may not party in this league."}]},{"id":"Sentinel","realm":"pc","url":"https://www.pathofexile.com/ladders/league/Sentinel","startAt":"2022-05-13T20:00:00Z","endAt":"2022-08-16T22:00:00Z","description":"Harness ancient Sentinels to control the risk and reward of combat.\n\nThis is the default Path of Exile league.","registerAt":"2022-05-13T17:30:00Z","delveEvent":true,"rules":[]},{"id":"Hardcore Sentinel","realm":"pc","url":"https://www.pathofexile.com/ladders/league/Hardcore+Sentinel","startAt":"2022-05-13T20:00:00Z","endAt":"2022-08-16T22:00:00Z","description":"Harness ancient Sentinels to control the risk and reward of combat.\n\nA character killed in Hardcore Sentinel becomes a Standard character.","registerAt":"2022-05-13T17:30:00Z","delveEvent":true,"rules":[{"id":"Hardcore","name":"Hardcore","description":"A character killed in Hardcore is moved to its parent league."}]},{"id":"SSF Sentinel","realm":"pc","url":"https://www.pathofexile.com/ladders/league/SSF+Sentinel","startAt":"2022-05-13T20:00:00Z","endAt":"2022-08-16T22:00:00Z","description":"SSF Sentinel","registerAt":"2022-05-13T17:30:00Z","delveEvent":true,"rules":[{"id":"NoParties","name":"Solo","description":"You may not party in this league."}]},{"id":"SSF Sentinel HC","realm":"pc","url":"https://www.pathofexile.com/ladders/league/SSF+Sentinel+HC","startAt":"2022-05-13T20:00:00Z","endAt":"2022-08-16T22:00:00Z","description":"SSF HC Sentinel","registerAt":"2022-05-13T17:30:00Z","delveEvent":true,"rules":[{"id":"Hardcore","name":"Hardcore","description":"A character killed in Hardcore is moved to its parent league."},{"id":"NoParties","name":"Solo","description":"You may not party in this league."}]}]